icare/__init__.py
icare/absolute_risk_main.py
icare/absolute_risk_model.py
icare/check_errors.py
icare/covariate_model.py
icare/design_matrix.py
icare/misc.py
icare/model_validation.py
icare/snp_model.py
icare/utils.py
pyicare-1.0.0.dist-info/LICENSE
pyicare-1.0.0.dist-info/METADATA
pyicare-1.0.0.dist-info/WHEEL
pyicare-1.0.0.dist-info/entry_points.txt
pyicare-1.0.0.dist-info/top_level.txt
pyicare-1.0.0.dist-info/RECORD
