Metadata-Version: 2.1
Name: pyicare
Version: 1.0.0
Summary: A Python distribution of iCARE, a tool for individualized Coherent Absolute Risk Estimation.
Author-email: Jeya Balaji Balasubramanian <jeyabbalas@gmail.com>
License: MIT License
Project-URL: Homepage, https://github.com/jeyabbalas/py-icare
Keywords: gwas,webassembly,survival-analysis,cox-proportional-hazard,genome-wide-association-studies,absolute-risk
Classifier: License :: OSI Approved :: MIT License
Classifier: Programming Language :: Python
Classifier: Programming Language :: Python :: 3
Classifier: Environment :: WebAssembly
Classifier: Topic :: Scientific/Engineering
Requires-Python: >=3.9
License-File: LICENSE
Requires-Dist: numpy (>=1.22.4)
Requires-Dist: pandas (>=1.5.3)
Requires-Dist: patsy (>=0.5.3)
Requires-Dist: scipy (>=1.9.3)
Provides-Extra: demo
Requires-Dist: matplotlib ; extra == 'demo'
Requires-Dist: requests ; extra == 'demo'
Requires-Dist: seaborn ; extra == 'demo'
Requires-Dist: statsmodels ; extra == 'demo'
Provides-Extra: dev
Requires-Dist: pytest ; extra == 'dev'
